daios/__init__.py
daios/__main__.py
daios/client.py
daios_sdk-0.0.12.dist-info/LICENSE
daios_sdk-0.0.12.dist-info/METADATA
daios_sdk-0.0.12.dist-info/WHEEL
daios_sdk-0.0.12.dist-info/top_level.txt
daios_sdk-0.0.12.dist-info/RECORD
